Workbook

Sheet Dashboard
B1: Retail Sales Dashboard — 2025
B2: Beginner-level analysis: 12 months, 4 regions, 4 categories, 12 products (synthetic dataset). All numbers update from the Clean Data sheet.
B4: TOTAL SALES | D4: TOTAL PROFIT | F4: PROFIT MARGIN | H4: ORDERS | J4: AVG ORDER VALUE | L4: PEAK MONTH
B5: =Analysis!E17 | D5: =Analysis!F17 | F5: =Analysis!G17 | H5: =Analysis!C17 | J5: =IFERROR(Analysis!E17/Analysis!C17,0) | L5: =INDEX(Analysis!A5:A16,MATCH(MAX(Analysis!E5:E16),Analysis!E5:E16,0))
B44: Key findings
B45: • Sales peak in Dec and are lowest in Aug; November and December together deliver 23% of annual sales, so the business is strongly seasonal.
B46: • Standing Desk is the top product by sales (₹11.7 lakh); the top 3 products contribute 38% of total sales. Desk Organizer is the weakest (₹2.8 lakh).
B47: • Furniture is the largest category by sales (33% share), while Accessories earns the best margin (39.0%) and Furniture the lowest (27.0%).
B48: • South is the strongest region (31% of sales) and East the weakest (15%).
B49: • Discounted orders earn a 28.4% margin versus 37.4% for full-price orders, so discounting has a real cost to profitability.
B51: See the Insights sheet for cleaning steps, metric choices and recommendations.

Sheet Analysis
A1: Sales Analysis (all figures are formulas on the Clean Data sheet)
A2: Currency: Indian Rupees (₹). Profit = Sales − Quantity × Unit Cost. Margin = Profit ÷ Sales.
A3: 1. Monthly trend
A4: Month | B4: Month # | C4: Orders | D4: Units | E4: Sales | F4: Profit | G4: Margin | H4: MoM Sales Growth
A5: Jan | B5: 1 | C5: =COUNTIFS('Clean Data'!$C$2:$C$1195,B5) | D5: =SUMIFS('Clean Data'!$G$2:$G$1195,'Clean Data'!$C$2:$C$1195,B5) | E5: =SUMIFS('Clean Data'!$K$2:$K$1195,'Clean Data'!$C$2:$C$1195,B5) | F5: =SUMIFS('Clean Data'!$L$2:$L$1195,'Clean Data'!$C$2:$C$1195,B5) | G5: =IFERROR(F5/E5,0) | H5: -
A6: Feb | B6: 2 | C6: =COUNTIFS('Clean Data'!$C$2:$C$1195,B6) | D6: =SUMIFS('Clean Data'!$G$2:$G$1195,'Clean Data'!$C$2:$C$1195,B6) | E6: =SUMIFS('Clean Data'!$K$2:$K$1195,'Clean Data'!$C$2:$C$1195,B6) | F6: =SUMIFS('Clean Data'!$L$2:$L$1195,'Clean Data'!$C$2:$C$1195,B6) | G6: =IFERROR(F6/E6,0) | H6: =IFERROR(E6/E5-1,0)
A7: Mar | B7: 3 | C7: =COUNTIFS('Clean Data'!$C$2:$C$1195,B7) | D7: =SUMIFS('Clean Data'!$G$2:$G$1195,'Clean Data'!$C$2:$C$1195,B7) | E7: =SUMIFS('Clean Data'!$K$2:$K$1195,'Clean Data'!$C$2:$C$1195,B7) | F7: =SUMIFS('Clean Data'!$L$2:$L$1195,'Clean Data'!$C$2:$C$1195,B7) | G7: =IFERROR(F7/E7,0) | H7: =IFERROR(E7/E6-1,0)
A8: Apr | B8: 4 | C8: =COUNTIFS('Clean Data'!$C$2:$C$1195,B8) | D8: =SUMIFS('Clean Data'!$G$2:$G$1195,'Clean Data'!$C$2:$C$1195,B8) | E8: =SUMIFS('Clean Data'!$K$2:$K$1195,'Clean Data'!$C$2:$C$1195,B8) | F8: =SUMIFS('Clean Data'!$L$2:$L$1195,'Clean Data'!$C$2:$C$1195,B8) | G8: =IFERROR(F8/E8,0) | H8: =IFERROR(E8/E7-1,0)
A9: May | B9: 5 | C9: =COUNTIFS('Clean Data'!$C$2:$C$1195,B9) | D9: =SUMIFS('Clean Data'!$G$2:$G$1195,'Clean Data'!$C$2:$C$1195,B9) | E9: =SUMIFS('Clean Data'!$K$2:$K$1195,'Clean Data'!$C$2:$C$1195,B9) | F9: =SUMIFS('Clean Data'!$L$2:$L$1195,'Clean Data'!$C$2:$C$1195,B9) | G9: =IFERROR(F9/E9,0) | H9: =IFERROR(E9/E8-1,0)
A10: Jun | B10: 6 | C10: =COUNTIFS('Clean Data'!$C$2:$C$1195,B10) | D10: =SUMIFS('Clean Data'!$G$2:$G$1195,'Clean Data'!$C$2:$C$1195,B10) | E10: =SUMIFS('Clean Data'!$K$2:$K$1195,'Clean Data'!$C$2:$C$1195,B10) | F10: =SUMIFS('Clean Data'!$L$2:$L$1195,'Clean Data'!$C$2:$C$1195,B10) | G10: =IFERROR(F10/E10,0) | H10: =IFERROR(E10/E9-1,0)
A11: Jul | B11: 7 | C11: =COUNTIFS('Clean Data'!$C$2:$C$1195,B11) | D11: =SUMIFS('Clean Data'!$G$2:$G$1195,'Clean Data'!$C$2:$C$1195,B11) | E11: =SUMIFS('Clean Data'!$K$2:$K$1195,'Clean Data'!$C$2:$C$1195,B11) | F11: =SUMIFS('Clean Data'!$L$2:$L$1195,'Clean Data'!$C$2:$C$1195,B11) | G11: =IFERROR(F11/E11,0) | H11: =IFERROR(E11/E10-1,0)
A12: Aug | B12: 8 | C12: =COUNTIFS('Clean Data'!$C$2:$C$1195,B12) | D12: =SUMIFS('Clean Data'!$G$2:$G$1195,'Clean Data'!$C$2:$C$1195,B12) | E12: =SUMIFS('Clean Data'!$K$2:$K$1195,'Clean Data'!$C$2:$C$1195,B12) | F12: =SUMIFS('Clean Data'!$L$2:$L$1195,'Clean Data'!$C$2:$C$1195,B12) | G12: =IFERROR(F12/E12,0) | H12: =IFERROR(E12/E11-1,0)
A13: Sep | B13: 9 | C13: =COUNTIFS('Clean Data'!$C$2:$C$1195,B13) | D13: =SUMIFS('Clean Data'!$G$2:$G$1195,'Clean Data'!$C$2:$C$1195,B13) | E13: =SUMIFS('Clean Data'!$K$2:$K$1195,'Clean Data'!$C$2:$C$1195,B13) | F13: =SUMIFS('Clean Data'!$L$2:$L$1195,'Clean Data'!$C$2:$C$1195,B13) | G13: =IFERROR(F13/E13,0) | H13: =IFERROR(E13/E12-1,0)
A14: Oct | B14: 10 | C14: =COUNTIFS('Clean Data'!$C$2:$C$1195,B14) | D14: =SUMIFS('Clean Data'!$G$2:$G$1195,'Clean Data'!$C$2:$C$1195,B14) | E14: =SUMIFS('Clean Data'!$K$2:$K$1195,'Clean Data'!$C$2:$C$1195,B14) | F14: =SUMIFS('Clean Data'!$L$2:$L$1195,'Clean Data'!$C$2:$C$1195,B14) | G14: =IFERROR(F14/E14,0) | H14: =IFERROR(E14/E13-1,0)
A15: Nov | B15: 11 | C15: =COUNTIFS('Clean Data'!$C$2:$C$1195,B15) | D15: =SUMIFS('Clean Data'!$G$2:$G$1195,'Clean Data'!$C$2:$C$1195,B15) | E15: =SUMIFS('Clean Data'!$K$2:$K$1195,'Clean Data'!$C$2:$C$1195,B15) | F15: =SUMIFS('Clean Data'!$L$2:$L$1195,'Clean Data'!$C$2:$C$1195,B15) | G15: =IFERROR(F15/E15,0) | H15: =IFERROR(E15/E14-1,0)
A16: Dec | B16: 12 | C16: =COUNTIFS('Clean Data'!$C$2:$C$1195,B16) | D16: =SUMIFS('Clean Data'!$G$2:$G$1195,'Clean Data'!$C$2:$C$1195,B16) | E16: =SUMIFS('Clean Data'!$K$2:$K$1195,'Clean Data'!$C$2:$C$1195,B16) | F16: =SUMIFS('Clean Data'!$L$2:$L$1195,'Clean Data'!$C$2:$C$1195,B16) | G16: =IFERROR(F16/E16,0) | H16: =IFERROR(E16/E15-1,0)
A17: Total | C17: =SUM(C5:C16) | D17: =SUM(D5:D16) | E17: =SUM(E5:E16) | F17: =SUM(F5:F16) | G17: =IFERROR(F17/E17,0)
A20: 2. Category performance
A21: Category | B21: Orders | C21: Units | D21: Sales | E21: Profit | F21: Margin | G21: Share of Sales
A22: Furniture | B22: =COUNTIFS('Clean Data'!$E$2:$E$1195,A22) | C22: =SUMIFS('Clean Data'!$G$2:$G$1195,'Clean Data'!$E$2:$E$1195,A22) | D22: =SUMIFS('Clean Data'!$K$2:$K$1195,'Clean Data'!$E$2:$E$1195,A22) | E22: =SUMIFS('Clean Data'!$L$2:$L$1195,'Clean Data'!$E$2:$E$1195,A22) | F22: =IFERROR(E22/D22,0) | G22: =IFERROR(D22/$D$26,0)
A23: Technology | B23: =COUNTIFS('Clean Data'!$E$2:$E$1195,A23) | C23: =SUMIFS('Clean Data'!$G$2:$G$1195,'Clean Data'!$E$2:$E$1195,A23) | D23: =SUMIFS('Clean Data'!$K$2:$K$1195,'Clean Data'!$E$2:$E$1195,A23) | E23: =SUMIFS('Clean Data'!$L$2:$L$1195,'Clean Data'!$E$2:$E$1195,A23) | F23: =IFERROR(E23/D23,0) | G23: =IFERROR(D23/$D$26,0)
A24: Accessories | B24: =COUNTIFS('Clean Data'!$E$2:$E$1195,A24) | C24: =SUMIFS('Clean Data'!$G$2:$G$1195,'Clean Data'!$E$2:$E$1195,A24) | D24: =SUMIFS('Clean Data'!$K$2:$K$1195,'Clean Data'!$E$2:$E$1195,A24) | E24: =SUMIFS('Clean Data'!$L$2:$L$1195,'Clean Data'!$E$2:$E$1195,A24) | F24: =IFERROR(E24/D24,0) | G24: =IFERROR(D24/$D$26,0)
A25: Office Supplies | B25: =COUNTIFS('Clean Data'!$E$2:$E$1195,A25) | C25: =SUMIFS('Clean Data'!$G$2:$G$1195,'Clean Data'!$E$2:$E$1195,A25) | D25: =SUMIFS('Clean Data'!$K$2:$K$1195,'Clean Data'!$E$2:$E$1195,A25) | E25: =SUMIFS('Clean Data'!$L$2:$L$1195,'Clean Data'!$E$2:$E$1195,A25) | F25: =IFERROR(E25/D25,0) | G25: =IFERROR(D25/$D$26,0)
A26: Total | B26: =SUM(B22:B25) | C26: =SUM(C22:C25) | D26: =SUM(D22:D25) | E26: =SUM(E22:E25) | F26: =IFERROR(E26/D26,0) | G26: =SUM(G22:G25)
A29: 3. Product performance (sorted by sales)
A30: Product | B30: Category | C30: Units | D30: Sales | E30: Profit | F30: Margin | G30: Sales Rank
A31: Standing Desk | B31: Furniture | C31: =SUMIFS('Clean Data'!$G$2:$G$1195,'Clean Data'!$F$2:$F$1195,A31) | D31: =SUMIFS('Clean Data'!$K$2:$K$1195,'Clean Data'!$F$2:$F$1195,A31) | E31: =SUMIFS('Clean Data'!$L$2:$L$1195,'Clean Data'!$F$2:$F$1195,A31) | F31: =IFERROR(E31/D31,0) | G31: =RANK(D31,$D$31:$D$42)
A32: Monitor 24" | B32: Technology | C32: =SUMIFS('Clean Data'!$G$2:$G$1195,'Clean Data'!$F$2:$F$1195,A32) | D32: =SUMIFS('Clean Data'!$K$2:$K$1195,'Clean Data'!$F$2:$F$1195,A32) | E32: =SUMIFS('Clean Data'!$L$2:$L$1195,'Clean Data'!$F$2:$F$1195,A32) | F32: =IFERROR(E32/D32,0) | G32: =RANK(D32,$D$31:$D$42)
A33: Printer Paper Box | B33: Office Supplies | C33: =SUMIFS('Clean Data'!$G$2:$G$1195,'Clean Data'!$F$2:$F$1195,A33) | D33: =SUMIFS('Clean Data'!$K$2:$K$1195,'Clean Data'!$F$2:$F$1195,A33) | E33: =SUMIFS('Clean Data'!$L$2:$L$1195,'Clean Data'!$F$2:$F$1195,A33) | F33: =IFERROR(E33/D33,0) | G33: =RANK(D33,$D$31:$D$42)
A34: Office Chair | B34: Furniture | C34: =SUMIFS('Clean Data'!$G$2:$G$1195,'Clean Data'!$F$2:$F$1195,A34) | D34: =SUMIFS('Clean Data'!$K$2:$K$1195,'Clean Data'!$F$2:$F$1195,A34) | E34: =SUMIFS('Clean Data'!$L$2:$L$1195,'Clean Data'!$F$2:$F$1195,A34) | F34: =IFERROR(E34/D34,0) | G34: =RANK(D34,$D$31:$D$42)
A35: Headphones | B35: Accessories | C35: =SUMIFS('Clean Data'!$G$2:$G$1195,'Clean Data'!$F$2:$F$1195,A35) | D35: =SUMIFS('Clean Data'!$K$2:$K$1195,'Clean Data'!$F$2:$F$1195,A35) | E35: =SUMIFS('Clean Data'!$L$2:$L$1195,'Clean Data'!$F$2:$F$1195,A35) | F35: =IFERROR(E35/D35,0) | G35: =RANK(D35,$D$31:$D$42)
A36: Bookshelf | B36: Furniture | C36: =SUMIFS('Clean Data'!$G$2:$G$1195,'Clean Data'!$F$2:$F$1195,A36) | D36: =SUMIFS('Clean Data'!$K$2:$K$1195,'Clean Data'!$F$2:$F$1195,A36) | E36: =SUMIFS('Clean Data'!$L$2:$L$1195,'Clean Data'!$F$2:$F$1195,A36) | F36: =IFERROR(E36/D36,0) | G36: =RANK(D36,$D$31:$D$42)
A37: Mechanical Keyboard | B37: Technology | C37: =SUMIFS('Clean Data'!$G$2:$G$1195,'Clean Data'!$F$2:$F$1195,A37) | D37: =SUMIFS('Clean Data'!$K$2:$K$1195,'Clean Data'!$F$2:$F$1195,A37) | E37: =SUMIFS('Clean Data'!$L$2:$L$1195,'Clean Data'!$F$2:$F$1195,A37) | F37: =IFERROR(E37/D37,0) | G37: =RANK(D37,$D$31:$D$42)
A38: Webcam | B38: Accessories | C38: =SUMIFS('Clean Data'!$G$2:$G$1195,'Clean Data'!$F$2:$F$1195,A38) | D38: =SUMIFS('Clean Data'!$K$2:$K$1195,'Clean Data'!$F$2:$F$1195,A38) | E38: =SUMIFS('Clean Data'!$L$2:$L$1195,'Clean Data'!$F$2:$F$1195,A38) | F38: =IFERROR(E38/D38,0) | G38: =RANK(D38,$D$31:$D$42)
A39: USB-C Hub | B39: Accessories | C39: =SUMIFS('Clean Data'!$G$2:$G$1195,'Clean Data'!$F$2:$F$1195,A39) | D39: =SUMIFS('Clean Data'!$K$2:$K$1195,'Clean Data'!$F$2:$F$1195,A39) | E39: =SUMIFS('Clean Data'!$L$2:$L$1195,'Clean Data'!$F$2:$F$1195,A39) | F39: =IFERROR(E39/D39,0) | G39: =RANK(D39,$D$31:$D$42)
A40: Wireless Mouse | B40: Technology | C40: =SUMIFS('Clean Data'!$G$2:$G$1195,'Clean Data'!$F$2:$F$1195,A40) | D40: =SUMIFS('Clean Data'!$K$2:$K$1195,'Clean Data'!$F$2:$F$1195,A40) | E40: =SUMIFS('Clean Data'!$L$2:$L$1195,'Clean Data'!$F$2:$F$1195,A40) | F40: =IFERROR(E40/D40,0) | G40: =RANK(D40,$D$31:$D$42)
A41: Notebook Set | B41: Office Supplies | C41: =SUMIFS('Clean Data'!$G$2:$G$1195,'Clean Data'!$F$2:$F$1195,A41) | D41: =SUMIFS('Clean Data'!$K$2:$K$1195,'Clean Data'!$F$2:$F$1195,A41) | E41: =SUMIFS('Clean Data'!$L$2:$L$1195,'Clean Data'!$F$2:$F$1195,A41) | F41: =IFERROR(E41/D41,0) | G41: =RANK(D41,$D$31:$D$42)
A42: Desk Organizer | B42: Office Supplies | C42: =SUMIFS('Clean Data'!$G$2:$G$1195,'Clean Data'!$F$2:$F$1195,A42) | D42: =SUMIFS('Clean Data'!$K$2:$K$1195,'Clean Data'!$F$2:$F$1195,A42) | E42: =SUMIFS('Clean Data'!$L$2:$L$1195,'Clean Data'!$F$2:$F$1195,A42) | F42: =IFERROR(E42/D42,0) | G42: =RANK(D42,$D$31:$D$42)
A45: 4. Regional performance
A46: Region | B46: Orders | C46: Sales | D46: Profit | E46: Margin | F46: Share of Sales
A47: South | B47: =COUNTIFS('Clean Data'!$D$2:$D$1195,A47) | C47: =SUMIFS('Clean Data'!$K$2:$K$1195,'Clean Data'!$D$2:$D$1195,A47) | D47: =SUMIFS('Clean Data'!$L$2:$L$1195,'Clean Data'!$D$2:$D$1195,A47) | E47: =IFERROR(D47/C47,0) | F47: =IFERROR(C47/$C$51,0)
A48: West | B48: =COUNTIFS('Clean Data'!$D$2:$D$1195,A48) | C48: =SUMIFS('Clean Data'!$K$2:$K$1195,'Clean Data'!$D$2:$D$1195,A48) | D48: =SUMIFS('Clean Data'!$L$2:$L$1195,'Clean Data'!$D$2:$D$1195,A48) | E48: =IFERROR(D48/C48,0) | F48: =IFERROR(C48/$C$51,0)
A49: North | B49: =COUNTIFS('Clean Data'!$D$2:$D$1195,A49) | C49: =SUMIFS('Clean Data'!$K$2:$K$1195,'Clean Data'!$D$2:$D$1195,A49) | D49: =SUMIFS('Clean Data'!$L$2:$L$1195,'Clean Data'!$D$2:$D$1195,A49) | E49: =IFERROR(D49/C49,0) | F49: =IFERROR(C49/$C$51,0)
A50: East | B50: =COUNTIFS('Clean Data'!$D$2:$D$1195,A50) | C50: =SUMIFS('Clean Data'!$K$2:$K$1195,'Clean Data'!$D$2:$D$1195,A50) | D50: =SUMIFS('Clean Data'!$L$2:$L$1195,'Clean Data'!$D$2:$D$1195,A50) | E50: =IFERROR(D50/C50,0) | F50: =IFERROR(C50/$C$51,0)
A51: Total | B51: =SUM(B47:B50) | C51: =SUM(C47:C50) | D51: =SUM(D47:D50) | E51: =IFERROR(D51/C51,0) | F51: =SUM(F47:F50)

Sheet Insights
B1: Insights, Method and Data Notes
B3: About the dataset
B4: • Retail office-products sales, January to December 2025, 4 regions, 4 categories, 12 products.
B5: • IMPORTANT: this is a synthetic (simulated) dataset generated for this exercise, with deliberately messy raw data. Replace it with a real dataset (for example a public Superstore or Kaggle sales file) if your submission needs real-world data.
B7: Data cleaning log
B8: Step | C8: Rows affected | D8: Notes
B9: Raw records loaded | C9: 1230 | D9: Starting point: 1,230 rows incl. duplicates and blanks
B10: Exact duplicate rows removed | C10: 30 | D10: Same Order ID and identical values
B11: Rows dropped: missing Quantity | C11: 6 | D11: Sales cannot be computed without a quantity
B12: Missing Unit Price filled | C12: 15 | D12: Filled with the product's standard (most common) price
B13: Region labels standardised | C13: 140 | D13: Trimmed spaces and fixed upper/lower case
B14: Text dates converted to real dates | C14: 300 | D14: Format DD-Mon-YYYY converted to Excel dates
B15: Final clean records | C15: 1194 | D15: Rows used in all analysis
B17: Metrics chosen and why
B18: • Sales = Quantity × Unit Price × (1 − Discount): the revenue actually collected per order.
B19: • Profit and Margin: show which products earn money, not just which sell most.
B20: • Orders and Average Order Value: separate demand volume from basket size.
B21: • Month-over-month growth and share of sales: reveal seasonality and concentration.
B23: Dashboard structure
B24: • Top row: six headline KPIs. Below: monthly trend (time), category (group), product (detail), region (geography). Each chart answers one business question and reads from the Analysis sheet, which reads from Clean Data via formulas.
B26: Key findings
B27: • Sales peak in Dec and are lowest in Aug; November and December together deliver 23% of annual sales, so the business is strongly seasonal.
B28: • Standing Desk is the top product by sales (₹11.7 lakh); the top 3 products contribute 38% of total sales. Desk Organizer is the weakest (₹2.8 lakh).
B29: • Furniture is the largest category by sales (33% share), while Accessories earns the best margin (39.0%) and Furniture the lowest (27.0%).
B30: • South is the strongest region (31% of sales) and East the weakest (15%).
... B38: • Set a discount cap for low-margin categories so promotions do not push orders below the target margin.

Sheet Clean Data
A1: Order ID | B1: Order Date | C1: Month | D1: Region | E1: Category | F1: Product | G1: Quantity | H1: Unit Price | I1: Discount | J1: Unit Cost | K1: Sales | L1: Profit
A2: ORD-10874 | B2: 45658 | C2: =MONTH(B2) | D2: West | E2: Technology | F2: Mechanical Keyboard | G2: 3 | H2: 4200 | I2: 0.15 | J2: 2500 | K2: =G2*H2*(1-I2) | L2: =K2-G2*J2
A3: ORD-10004 | B3: 45659 | C3: =MONTH(B3) | D3: North | E3: Accessories | F3: Webcam | G3: 1 | H3: 3200 | I3: 0 | J3: 1900 | K3: =G3*H3*(1-I3) | L3: =K3-G3*J3
A4: ORD-10244 | B4: 45659 | C4: =MONTH(B4) | D4: West | E4: Technology | F4: Mechanical Keyboard | G4: 1 | H4: 4200 | I4: 0.1 | J4: 2500 | K4: =G4*H4*(1-I4) | L4: =K4-G4*J4
A5: ORD-10728 | B5: 45659 | C5: =MONTH(B5) | D5: South | E5: Accessories | F5: Headphones | G5: 2 | H5: 4500 | I5: 0.05 | J5: 2600 | K5: =G5*H5*(1-I5) | L5: =K5-G5*J5
A6: ORD-10789 | B6: 45660 | C6: =MONTH(B6) | D6: South | E6: Office Supplies | F6: Printer Paper Box | G6: 4 | H6: 1600 | I6: 0 | J6: 1050 | K6: =G6*H6*(1-I6) | L6: =K6-G6*J6
A7: ORD-10898 | B7: 45660 | C7: =MONTH(B7) | D7: South | E7: Furniture | F7: Standing Desk | G7: 2 | H7: 19500 | I7: 0 | J7: 13800 | K7: =G7*H7*(1-I7) | L7: =K7-G7*J7
A8: ORD-10157 | B8: 45661 | C8: =MONTH(B8) | D8: West | E8: Accessories | F8: Headphones | G8: 3 | H8: 4500 | I8: 0 | J8: 2600 | K8: =G8*H8*(1-I8) | L8: =K8-G8*J8
A9: ORD-10877 | B9: 45661 | C9: =MONTH(B9) | D9: South | E9: Technology | F9: Wireless Mouse | G9: 4 | H9: 1200 | I9: 0 | J9: 650 | K9: =G9*H9*(1-I9) | L9: =K9-G9*J9
A10: ORD-10891 | B10: 45661 | C10: =MONTH(B10) | D10: West | E10: Accessories | F10: Webcam | G10: 2 | H10: 3200 | I10: 0 | J10: 1900 | K10: =G10*H10*(1-I10) | L10: =K10-G10*J10
A11: ORD-10051 | B11: 45662 | C11: =MONTH(B11) | D11: South | E11: Office Supplies | F11: Printer Paper Box | G11: 6 | H11: 1600 | I11: 0.2 | J11: 1050 | K11: =G11*H11*(1-I11) | L11: =K11-G11*J11
A12: ORD-10315 | B12: 45662 | C12: =MONTH(B12) | D12: South | E12: Technology | F12: Wireless Mouse | G12: 1 | H12: 1200 | I12: 0 | J12: 650 | K12: =G12*H12*(1-I12) | L12: =K12-G12*J12
A13: ORD-10469 | B13: 45662 | C13: =MONTH(B13) | D13: West | E13: Accessories | F13: Webcam | G13: 2 | H13: 3200 | I13: 0 | J13: 1900 | K13: =G13*H13*(1-I13) | L13: =K13-G13*J13
... A1195: ORD-10552 | B1195: 46019 | C1195: =MONTH(B1195) | D1195: West | E1195: Accessories | F1195: Headphones | G1195: 3 | H1195: 4500 | I1195: 0.15 | J1195: 2600 | K1195: =G1195*H1195*(1-I1195) | L1195: =K1195-G1195*J1195

Sheet Raw Data
A1: Order ID | B1: Order Date | C1: Region | D1: Category | E1: Product | F1: Quantity | G1: Unit Price | H1: Discount | I1: Unit Cost
A2: ORD-10582 | B2: 08-May-2025 | C2: West | D2: Office Supplies | E2: Desk Organizer | F2: 1 | G2: 850 | H2: 0 | I2: 420
A3: ORD-11076 | B3: 24-May-2025 | C3: south | D3: Technology | E3: Wireless Mouse | F3: 5 | G3: 1200 | H3: 0 | I3: 650
A4: ORD-11129 | B4: 45877 | C4: West | D4: Office Supplies | E4: Notebook Set | F4: 7 | G4: 450 | H4: 0.05 | I4: 190
A5: ORD-10986 | B5: 45664 | C5: North | D5: Accessories | E5: USB-C Hub | F5: 2 | G5: 1800 | H5: 0.15 | I5: 980
A6: ORD-10635 | B6: 45908 | C6: East | D6: Technology | E6: Mechanical Keyboard | F6: 2 | G6: 4200 | H6: 0 | I6: 2500
A7: ORD-10724 | B7: 45949 | C7: East | D7: Accessories | E7: USB-C Hub | F7: 4 | G7: 1800 | H7: 0 | I7: 980
A8: ORD-10123 | B8: 45665 | C8: West | D8: Accessories | E8: Headphones | F8: 1 | G8: 4500 | H8: 0 | I8: 2600
A9: ORD-10445 | B9: 45693 | C9: North | D9: Technology | E9: Wireless Mouse | F9: 5 | G9: 1200 | H9: 0.2 | I9: 650
A10: ORD-10142 | B10: 45817 | C10: North | D10: Furniture | E10: Bookshelf | F10: 2 | G10: 6200 | H10: 0.2 | I10: 4100
A11: ORD-10524 | B11: 45755 | C11: East | D11: Furniture | E11: Office Chair | F11: 2 | G11: 8500 | H11: 0.05 | I11: 5600
A12: ORD-10099 | B12: 45945 | C12: West | D12: Accessories | E12: Webcam | F12: 2 | G12: 3200 | H12: 0.05 | I12: 1900
A13: ORD-11099 | B13: 45843 | C13: East | D13: Accessories | E13: Webcam | F13: 1 | G13: 3200 | H13: 0.2 | I13: 1900
A14: ORD-10978 | B14: 07-Dec-2025 | C14: West | D14: Accessories | E14: Headphones | F14: 3 | G14: 4500 | H14: 0.1 | I14: 2600
A15: ORD-10546 | B15: 46002 | C15: West | D15: Office Supplies | E15: Printer Paper Box | F15: 3 | G15: 1600 | H15: 0.2 | I15: 1050
A16: ORD-10012 | B16: 45790 | C16: West | D16: Technology | E16: Monitor 24" | F16: 1 | G16: 11500 | H16: 0.05 | I16: 8200
A17: ORD-10880 | B17: 45697 | C17: East | D17: Office Supplies | E17: Printer Paper Box | F17: 2 | G17: 1600 | H17: 0 | I17: 1050
A18: ORD-10264 | B18: 45823 | C18: West | D18: Technology | E18: Mechanical Keyboard | F18: 2 | G18: 4200 | H18: 0 | I18: 2500
A19: ORD-10688 | B19: 45761 | C19: North | D19: Accessories | E19: Webcam | F19: 1 | G19: 3200 | H19: 0 | I19: 1900
A20: ORD-10520 | B20: 45704 | C20: South | D20: Technology | E20: Mechanical Keyboard | F20: 3 | G20: 4200 | H20: 0.15 | I20: 2500
A21: ORD-10499 | B21: 46009 | C21: EAST | D21: Furniture | E21: Bookshelf | F21: 1 | G21: 6200 | H21: 0.1 | I21: 4100
A22: ORD-10836 | B22: 45835 | C22: North | D22: Accessories | E22: Webcam | F22: 1 | G22: 3200 | H22: 0 | I22: 1900
A23: ORD-10937 | B23: 45885 | C23: West | D23: Accessories | E23: USB-C Hub | F23: 4 | G23: 1800 | H23: 0 | I23: 980
A24: ORD-10089 | B24: 27-Oct-2025 | C24: South | D24: Technology | E24: Monitor 24" | F24: 2 | G24: 11500 | H24: 0 | I24: 8200
A25: ORD-10177 | B25: 45901 | C25: North | D25: Technology | E25: Wireless Mouse | F25: 1 | G25: 1200 | H25: 0.05 | I25: 650
A26: ORD-10783 | B26: 45978 | C26: East | D26: Office Supplies | E26: Notebook Set | F26: 7 | G26: 450 | H26: 0.15 | I26: 190
A27: ORD-10606 | B27: 45845 | C27: North | D27: Office Supplies | E27: Notebook Set | F27: 4 | G27: 450 | H27: 0.2 | I27: 190
A28: ORD-10999 | B28: 45998 | C28: South | D28: Furniture | E28: Standing Desk | F28: 2 | G28: 19500 | H28: 0 | I28: 13800
A29: ORD-10034 | B29: 45740 | C29: South | D29: Accessories | E29: USB-C Hub | F29: 3 | G29: 1800 | H29: 0 | I29: 980
A30: ORD-10416 | B30: 45774 | C30: East | D30: Office Supplies | E30: Notebook Set | F30: 8 | H30: 0 | I30: 190
A31: ORD-10820 | B31: 17-Dec-2025 | C31: North | D31: Accessories | E31: Headphones | F31: 1 | G31: 4500 | H31: 0.15 | I31: 2600
A32: ORD-10388 | B32: 45962 | C32: North | D32: Technology | E32: Wireless Mouse | F32: 3 | G32: 1200 | H32: 0.05 | I32: 650
A33: ORD-10158 | B33: 45980 | C33: West | D33: Office Supplies | E33: Desk Organizer | F33: 4 | G33: 850 | H33: 0.15 | I33: 420
A34: ORD-10917 | B34: 20-Sep-2025 | C34: North | D34: Office Supplies | E34: Desk Organizer | F34: 5 | G34: 850 | H34: 0.15 | I34: 420
A35: ORD-11035 | B35: 45730 | C35: West | D35: Technology | E35: Mechanical Keyboard | F35: 1 | G35: 4200 | H35: 0 | I35: 2500
A36: ORD-10358 | B36: 45832 | C36: South | D36: Accessories | E36: Headphones | F36: 2 | G36: 4500 | H36: 0 | I36: 2600
A37: ORD-10151 | B37: 45669 | C37: West | D37: Office Supplies | E37: Notebook Set | F37: 4 | G37: 450 | H37: 0 | I37: 190
A38: ORD-10892 | B38: 14-Jul-2025 | C38: East | D38: Office Supplies | E38: Printer Paper Box | F38: 6 | G38: 1600 | H38: 0.05 | I38: 1050
A39: ORD-10616 | B39: 46009 | C39: South | D39: Technology | E39: Wireless Mouse | F39: 5 | G39: 1200 | H39: 0.15 | I39: 650
A40: ORD-10949 | B40: 45920 | C40: South | D40: Technology | E40: Wireless Mouse | F40: 5 | G40: 1200 | H40: 0.05 | I40: 650
A41: ORD-11173 | B41: 05-Dec-2025 | C41: West | D41: Office Supplies | E41: Desk Organizer | F41: 5 | G41: 850 | H41: 0 | I41: 420
A42: ORD-10641 | B42: 45928 | C42: South | D42: Office Supplies | E42: Desk Organizer | F42: 5 | G42: 850 | H42: 0.2 | I42: 420
A43: ORD-10950 | B43: 45812 | C43: south | D43: Accessories | E43: USB-C Hub | F43: 4 | G43: 1800 | H43: 0 | I43: 980
A44: ORD-11152 | B44: 45889 | C44: South | D44: Technology | E44: Mechanical Keyboard | F44: 1 | G44: 4200 | H44: 0 | I44: 2500
A45: ORD-10764 | B45: 10-May-2025 | C45: West | D45: Technology | E45: Mechanical Keyboard | F45: 1 | G45: 4200 | H45: 0.15 | I45: 2500
A46: ORD-10279 | B46: 45727 | C46: West | D46: Furniture | E46: Office Chair | F46: 1 | G46: 8500 | H46: 0.2 | I46: 5600
A47: ORD-10488 | B47: 45662 | C47: SOUTH | D47: Technology | E47: Mechanical Keyboard | F47: 1 | G47: 4200 | H47: 0 | I47: 2500
A48: ORD-10072 | B48: 45876 | C48: north | D48: Technology | E48: Mechanical Keyboard | F48: 3 | G48: 4200 | H48: 0.1 | I48: 2500
A49: ORD-10074 | B49: 45925 | C49: South | D49: Office Supplies | E49: Notebook Set | F49: 2 | G49: 450 | H49: 0 | I49: 190
A50: ORD-10013 | B50: 45858 | C50: East | D50: Accessories | E50: USB-C Hub | F50: 3 | G50: 1800 | H50: 0 | I50: 980
A51: ORD-10220 | B51: 45943 | C51: North | D51: Furniture | E51: Standing Desk | F51: 1 | G51: 19500 | H51: 0.2 | I51: 13800
A52: ORD-11037 | B52: 45762 | C52: West | D52: Accessories | E52: Webcam | F52: 2 | G52: 3200 | H52: 0.1 | I52: 1900
A53: ORD-10183 | B53: 46015 | C53: north | D53: Technology | E53: Monitor 24" | F53: 1 | G53: 11500 | H53: 0 | I53: 8200
A54: ORD-10094 | B54: 45969 | C54: West | D54: Office Supplies | E54: Printer Paper Box | F54: 2 | G54: 1600 | H54: 0 | I54: 1050
A55: ORD-10379 | B55: 45910 | C55: West | D55: Office Supplies | E55: Notebook Set | F55: 7 | G55: 450 | H55: 0.15 | I55: 190
A56: ORD-10440 | B56: 20-Jan-2025 | C56: East | D56: Technology | E56: Wireless Mouse | F56: 4 | G56: 1200 | H56: 0 | I56: 650
A57: ORD-10752 | B57: 45685 | C57: South | D57: Technology | E57: Monitor 24" | F57: 1 | G57: 11500 | H57: 0.2 | I57: 8200
A58: ORD-11080 | B58: 45849 | C58: West | D58: Office Supplies | E58: Desk Organizer | F58: 5 | G58: 850 | H58: 0 | I58: 420
A59: ORD-10153 | B59: 45937 | C59: North | D59: Accessories | E59: Headphones | F59: 1 | G59: 4500 | H59: 0 | I59: 2600
A60: ORD-10960 | B60: 45835 | C60: North | D60: Office Supplies | E60: Notebook Set | F60: 3 | G60: 450 | H60: 0.05 | I60: 190
A61: ORD-10729 | B61: 45957 | C61: West | D61: Office Supplies | E61: Desk Organizer | F61: 1 | G61: 850 | H61: 0.2 | I61: 420
A62: ORD-10016 | B62: 45915 | C62: SOUTH | D62: Technology | E62: Wireless Mouse | F62: 3 | G62: 1200 | H62: 0 | I62: 650
A63: ORD-10561 | B63: 21-Dec-2025 | C63: East | D63: Accessories | E63: Headphones | F63: 2 | G63: 4500 | H63: 0.1 | I63: 2600
A64: ORD-10894 | B64: 45919 | C64: North | D64: Office Supplies | E64: Printer Paper Box | F64: 5 | G64: 1600 | H64: 0.2 | I64: 1050
A65: ORD-11145 | B65: 45845 | C65: South | D65: Technology | E65: Wireless Mouse | F65: 5 | G65: 1200 | H65: 0.1 | I65: 650
A66: ORD-10899 | B66: 45943 | C66: West | D66: Furniture | E66: Standing Desk | F66: 2 | G66: 19500 | H66: 0.2 | I66: 13800
A67: ORD-11067 | B67: 45873 | C67: North | D67: Office Supplies | E67: Notebook Set | F67: 4 | G67: 450 | H67: 0.15 | I67: 190
A68: ORD-10387 | B68: 27-Mar-2025 | C68: South | D68: Office Supplies | E68: Notebook Set | F68: 2 | G68: 450 | H68: 0.15 | I68: 190
A69: ORD-11006 | B69: 10-Jan-2025 | C69: North | D69: Furniture | E69: Standing Desk | F69: 2 | G69: 19500 | H69: 0.2 | I69: 13800
A70: ORD-10038 | B70: 45946 | C70: West | D70: Office Supplies | E70: Desk Organizer | F70: 1 | G70: 850 | H70: 0 | I70: 420
A71: ORD-10230 | B71: 45678 | C71: West | D71: Furniture | E71: Bookshelf | F71: 1 | G71: 6200 | H71: 0.2 | I71: 4100
A72: ORD-10435 | B72: 45967 | C72: South | D72: Accessories | E72: Headphones | F72: 2 | G72: 4500 | H72: 0.2 | I72: 2600
A73: ORD-10811 | B73: 45846 | C73: East | D73: Furniture | E73: Standing Desk | F73: 2 | G73: 19500 | H73: 0.1 | I73: 13800
A74: ORD-10716 | B74: 45854 | C74: North | D74: Office Supplies | E74: Notebook Set | F74: 5 | G74: 450 | H74: 0 | I74: 190
A75: ORD-10258 | B75: 45677 | C75: South | D75: Furniture | E75: Office Chair | F75: 2 | G75: 8500 | H75: 0 | I75: 5600
A76: ORD-11045 | B76: 45974 | C76: West | D76: Technology | E76: Monitor 24" | F76: 1 | G76: 11500 | H76: 0.2 | I76: 8200
A77: ORD-10720 | B77: 45763 | C77: South | D77: Office Supplies | E77: Desk Organizer | F77: 4 | G77: 850 | H77: 0.2 | I77: 420
A78: ORD-10110 | B78: 45904 | C78: East | D78: Accessories | E78: USB-C Hub | F78: 3 | G78: 1800 | H78: 0.05 | I78: 980
A79: ORD-10708 | B79: 19-Aug-2025 | C79: South | D79: Accessories | E79: Headphones | F79: 1 | G79: 4500 | H79: 0.1 | I79: 2600
A80: ORD-11196 | B80: 45835 | C80: South | D80: Technology | E80: Wireless Mouse | F80: 2 | G80: 1200 | H80: 0.2 | I80: 650
A81: ORD-11014 | B81: 45943 | C81: West | D81: Accessories | E81: Headphones | F81: 3 | G81: 4500 | H81: 0.2 | I81: 2600
A82: ORD-11171 | B82: 45936 | C82: West | D82: Furniture | E82: Standing Desk | F82: 2 | G82: 19500 | H82: 0 | I82: 13800
A83: ORD-10505 | B83: 45752 | C83: South | D83: Office Supplies | E83: Notebook Set | F83: 6 | G83: 450 | H83: 0.2 | I83: 190
A84: ORD-10885 | B84: 45834 | C84: South | D84: Technology | E84: Monitor 24" | F84: 1 | G84: 11500 | H84: 0 | I84: 8200
A85: ORD-10274 | B85: 45690 | C85: West | D85: Office Supplies | E85: Desk Organizer | F85: 5 | G85: 850 | H85: 0.1 | I85: 420
A86: ORD-10261 | B86: 45926 | C86: East | D86: Technology | E86: Monitor 24" | F86: 2 | G86: 11500 | H86: 0.05 | I86: 8200
A87: ORD-10841 | B87: 45823 | C87: West | D87: Accessories | E87: Headphones | F87: 1 | G87: 4500 | H87: 0 | I87: 2600
A88: ORD-10673 | B88: 45950 | C88: South | D88: Office Supplies | E88: Notebook Set | F88: 4 | G88: 450 | H88: 0.2 | I88: 190
A89: ORD-10494 | B89: 45942 | C89: South | D89: Office Supplies | E89: Notebook Set | F89: 1 | G89: 450 | H89: 0 | I89: 190
A90: ORD-11055 | B90: 45782 | C90: west | D90: Accessories | E90: Headphones | F90: 2 | G90: 4500 | H90: 0.05 | I90: 2600
A91: ORD-10827 | B91: 04-Apr-2025 | C91: South | D91: Technology | E91: Monitor 24" | F91: 2 | G91: 11500 | H91: 0 | I91: 8200
A92: ORD-10613 | B92: 45834 | C92: west | D92: Office Supplies | E92: Printer Paper Box | F92: 6 | G92: 1600 | H92: 0.2 | I92: 1050
A93: ORD-10166 | B93: 24-Jun-2025 | C93: East | D93: Office Supplies | E93: Desk Organizer | F93: 5 | G93: 850 | H93: 0.05 | I93: 420
A94: ORD-10572 | B94: 02-Oct-2025 | C94: EAST | D94: Office Supplies | E94: Printer Paper Box | F94: 5 | G94: 1600 | H94: 0.2 | I94: 1050
A95: ORD-10497 | B95: 09-May-2025 | C95: West | D95: Office Supplies | E95: Printer Paper Box | F95: 6 | G95: 1600 | H95: 0.1 | I95: 1050
A96: ORD-10032 | B96: 45979 | C96: North | D96: Technology | E96: Monitor 24" | F96: 2 | G96: 11500 | H96: 0.1 | I96: 8200
A97: ORD-10180 | B97: 46015 | C97: South | D97: Office Supplies | E97: Printer Paper Box | F97: 5 | G97: 1600 | H97: 0.1 | I97: 1050
A98: ORD-11034 | B98: 24-Apr-2025 | C98: North | D98: Technology | E98: Mechanical Keyboard | F98: 3 | G98: 4200 | H98: 0 | I98: 2500
A99: ORD-10614 | B99: 11-Jun-2025 | C99: South | D99: Technology | E99: Mechanical Keyboard | F99: 1 | G99: 4200 | H99: 0.1 | I99: 2500
A100: ORD-10627 | B100: 45700 | C100: East | D100: Furniture | E100: Bookshelf | F100: 1 | G100: 6200 | H100: 0.2 | I100: 4100
...
